<?xml version="1.0" encoding="utf-8"?>
<base>
  <Current_Tuning>
    <kMagicPointsRequired value="0">
      <!--The amount of MP this interaction consumes.-->
    </kMagicPointsRequired>
    <kRadiusToExtinguish value="60">
      <!--The radius around the Unicorn that fires will get extinguished.-->
    </kRadiusToExtinguish>
    <kGlowVfxRgb value="0, 0.4, 1">
      <!--The RGB value for the unicorn's glow effect.-->
    </kGlowVfxRgb>
    <kRoutingDistance value="6">
      <!--The radius to route to the fire before extinguishing it. 0.0+-->
    </kRoutingDistance>
  </Current_Tuning>
</base>