<?xml version="1.0" encoding="utf-8"?>
<base>
  <Current_Tuning>
    <kTargetLookAtPriority value="80" />
    <kHowLongToWaitForOtherToArrive value="60" />
    <kMinDistanceToMoveAwayWhenRejected value="2">
      <!--The minimum distance a sim will move away when rejected-->
    </kMinDistanceToMoveAwayWhenRejected>
    <kMaxDistanceToMoveAwayWhenRejected value="4">
      <!--The maximum distance a sim will move away when rejected-->
    </kMaxDistanceToMoveAwayWhenRejected>
  </Current_Tuning>
</base>